{"id":"app/js/validation/dailyNoteValidate.js","dependencies":[{"name":"/run/media/veigaribo/BigStorage/Dev/JS/Sem Contrato Projeto 1/Projeto_1_SEMCONTRATO_FRONT/package.json","includedInParent":true,"mtime":1563772027360}],"generated":{"js":"'use strict';\n\nObject.defineProperty(exports, \"__esModule\", {\n    value: true\n});\nexports.yesterday = yesterday;\nexports.today = today;\nexports.impediment = impediment;\nfunction yesterday(first) {\n    if (!(first.value.trim().length > 3)) {\n        return 'Descrição muito pequena.';\n    } else {\n        return null;\n    }\n}\nfunction today(today) {\n    if (!(today.value.trim().length > 3)) {\n        return 'Descrição muito pequena.';\n    } else {\n        return null;\n    }\n}\nfunction impediment(third) {\n    if (!(third.value.trim().length > 3)) {\n        return 'Descrição muito pequena.';\n    } else {\n        return null;\n    }\n}","map":{"mappings":[{"name":"yesterday","generated":{"line":6,"column":8},"source":"app/js/validation/dailyNoteValidate.js","original":{"line":1,"column":16}},{"name":"yesterday","generated":{"line":6,"column":20},"source":"app/js/validation/dailyNoteValidate.js","original":{"line":1,"column":16}},{"name":"today","generated":{"line":7,"column":8},"source":"app/js/validation/dailyNoteValidate.js","original":{"line":9,"column":16}},{"name":"today","generated":{"line":7,"column":16},"source":"app/js/validation/dailyNoteValidate.js","original":{"line":9,"column":16}},{"name":"impediment","generated":{"line":8,"column":8},"source":"app/js/validation/dailyNoteValidate.js","original":{"line":17,"column":16}},{"name":"impediment","generated":{"line":8,"column":21},"source":"app/js/validation/dailyNoteValidate.js","original":{"line":17,"column":16}},{"generated":{"line":9,"column":0},"source":"app/js/validation/dailyNoteValidate.js","original":{"line":1,"column":7}},{"name":"yesterday","generated":{"line":9,"column":9},"source":"app/js/validation/dailyNoteValidate.js","original":{"line":1,"column":16}},{"generated":{"line":9,"column":18},"source":"app/js/validation/dailyNoteValidate.js","original":{"line":1,"column":7}},{"name":"first","generated":{"line":9,"column":19},"source":"app/js/validation/dailyNoteValidate.js","original":{"line":1,"column":26}},{"generated":{"line":9,"column":24},"source":"app/js/validation/dailyNoteValidate.js","original":{"line":1,"column":7}},{"generated":{"line":9,"column":26},"source":"app/js/validation/dailyNoteValidate.js","original":{"line":1,"column":33}},{"generated":{"line":10,"column":0},"source":"app/js/validation/dailyNoteValidate.js","original":{"line":2,"column":4}},{"generated":{"line":10,"column":8},"source":"app/js/validation/dailyNoteValidate.js","original":{"line":2,"column":8}},{"name":"first","generated":{"line":10,"column":10},"source":"app/js/validation/dailyNoteValidate.js","original":{"line":2,"column":10}},{"name":"value","generated":{"line":10,"column":16},"source":"app/js/validation/dailyNoteValidate.js","original":{"line":2,"column":16}},{"generated":{"line":10,"column":21},"source":"app/js/validation/dailyNoteValidate.js","original":{"line":2,"column":10}},{"name":"trim","generated":{"line":10,"column":22},"source":"app/js/validation/dailyNoteValidate.js","original":{"line":2,"column":22}},{"generated":{"line":10,"column":26},"source":"app/js/validation/dailyNoteValidate.js","original":{"line":2,"column":10}},{"name":"length","generated":{"line":10,"column":29},"source":"app/js/validation/dailyNoteValidate.js","original":{"line":2,"column":29}},{"generated":{"line":10,"column":35},"source":"app/js/validation/dailyNoteValidate.js","original":{"line":2,"column":10}},{"generated":{"line":10,"column":38},"source":"app/js/validation/dailyNoteValidate.js","original":{"line":2,"column":38}},{"generated":{"line":10,"column":39},"source":"app/js/validation/dailyNoteValidate.js","original":{"line":2,"column":8}},{"generated":{"line":10,"column":40},"source":"app/js/validation/dailyNoteValidate.js","original":{"line":2,"column":4}},{"generated":{"line":10,"column":42},"source":"app/js/validation/dailyNoteValidate.js","original":{"line":2,"column":42}},{"generated":{"line":11,"column":0},"source":"app/js/validation/dailyNoteValidate.js","original":{"line":3,"column":8}},{"generated":{"line":11,"column":15},"source":"app/js/validation/dailyNoteValidate.js","original":{"line":3,"column":15}},{"generated":{"line":11,"column":41},"source":"app/js/validation/dailyNoteValidate.js","original":{"line":3,"column":8}},{"generated":{"line":12,"column":0},"source":"app/js/validation/dailyNoteValidate.js","original":{"line":4,"column":5}},{"generated":{"line":12,"column":5},"source":"app/js/validation/dailyNoteValidate.js","original":{"line":2,"column":4}},{"generated":{"line":12,"column":11},"source":"app/js/validation/dailyNoteValidate.js","original":{"line":5,"column":9}},{"generated":{"line":13,"column":0},"source":"app/js/validation/dailyNoteValidate.js","original":{"line":6,"column":8}},{"generated":{"line":13,"column":15},"source":"app/js/validation/dailyNoteValidate.js","original":{"line":6,"column":15}},{"generated":{"line":13,"column":19},"source":"app/js/validation/dailyNoteValidate.js","original":{"line":6,"column":8}},{"generated":{"line":14,"column":0},"source":"app/js/validation/dailyNoteValidate.js","original":{"line":7,"column":5}},{"generated":{"line":15,"column":0},"source":"app/js/validation/dailyNoteValidate.js","original":{"line":8,"column":1}},{"generated":{"line":16,"column":0},"source":"app/js/validation/dailyNoteValidate.js","original":{"line":9,"column":7}},{"name":"today","generated":{"line":16,"column":9},"source":"app/js/validation/dailyNoteValidate.js","original":{"line":9,"column":16}},{"generated":{"line":16,"column":14},"source":"app/js/validation/dailyNoteValidate.js","original":{"line":9,"column":7}},{"name":"today","generated":{"line":16,"column":15},"source":"app/js/validation/dailyNoteValidate.js","original":{"line":9,"column":22}},{"generated":{"line":16,"column":20},"source":"app/js/validation/dailyNoteValidate.js","original":{"line":9,"column":7}},{"generated":{"line":16,"column":22},"source":"app/js/validation/dailyNoteValidate.js","original":{"line":9,"column":29}},{"generated":{"line":17,"column":0},"source":"app/js/validation/dailyNoteValidate.js","original":{"line":10,"column":4}},{"generated":{"line":17,"column":8},"source":"app/js/validation/dailyNoteValidate.js","original":{"line":10,"column":8}},{"name":"today","generated":{"line":17,"column":10},"source":"app/js/validation/dailyNoteValidate.js","original":{"line":10,"column":10}},{"name":"value","generated":{"line":17,"column":16},"source":"app/js/validation/dailyNoteValidate.js","original":{"line":10,"column":16}},{"generated":{"line":17,"column":21},"source":"app/js/validation/dailyNoteValidate.js","original":{"line":10,"column":10}},{"name":"trim","generated":{"line":17,"column":22},"source":"app/js/validation/dailyNoteValidate.js","original":{"line":10,"column":22}},{"generated":{"line":17,"column":26},"source":"app/js/validation/dailyNoteValidate.js","original":{"line":10,"column":10}},{"name":"length","generated":{"line":17,"column":29},"source":"app/js/validation/dailyNoteValidate.js","original":{"line":10,"column":29}},{"generated":{"line":17,"column":35},"source":"app/js/validation/dailyNoteValidate.js","original":{"line":10,"column":10}},{"generated":{"line":17,"column":38},"source":"app/js/validation/dailyNoteValidate.js","original":{"line":10,"column":38}},{"generated":{"line":17,"column":39},"source":"app/js/validation/dailyNoteValidate.js","original":{"line":10,"column":8}},{"generated":{"line":17,"column":40},"source":"app/js/validation/dailyNoteValidate.js","original":{"line":10,"column":4}},{"generated":{"line":17,"column":42},"source":"app/js/validation/dailyNoteValidate.js","original":{"line":10,"column":42}},{"generated":{"line":18,"column":0},"source":"app/js/validation/dailyNoteValidate.js","original":{"line":11,"column":8}},{"generated":{"line":18,"column":15},"source":"app/js/validation/dailyNoteValidate.js","original":{"line":11,"column":15}},{"generated":{"line":18,"column":41},"source":"app/js/validation/dailyNoteValidate.js","original":{"line":11,"column":8}},{"generated":{"line":19,"column":0},"source":"app/js/validation/dailyNoteValidate.js","original":{"line":12,"column":5}},{"generated":{"line":19,"column":5},"source":"app/js/validation/dailyNoteValidate.js","original":{"line":10,"column":4}},{"generated":{"line":19,"column":11},"source":"app/js/validation/dailyNoteValidate.js","original":{"line":13,"column":9}},{"generated":{"line":20,"column":0},"source":"app/js/validation/dailyNoteValidate.js","original":{"line":14,"column":8}},{"generated":{"line":20,"column":15},"source":"app/js/validation/dailyNoteValidate.js","original":{"line":14,"column":15}},{"generated":{"line":20,"column":19},"source":"app/js/validation/dailyNoteValidate.js","original":{"line":14,"column":8}},{"generated":{"line":21,"column":0},"source":"app/js/validation/dailyNoteValidate.js","original":{"line":15,"column":5}},{"generated":{"line":22,"column":0},"source":"app/js/validation/dailyNoteValidate.js","original":{"line":16,"column":1}},{"generated":{"line":23,"column":0},"source":"app/js/validation/dailyNoteValidate.js","original":{"line":17,"column":7}},{"name":"impediment","generated":{"line":23,"column":9},"source":"app/js/validation/dailyNoteValidate.js","original":{"line":17,"column":16}},{"generated":{"line":23,"column":19},"source":"app/js/validation/dailyNoteValidate.js","original":{"line":17,"column":7}},{"name":"third","generated":{"line":23,"column":20},"source":"app/js/validation/dailyNoteValidate.js","original":{"line":17,"column":27}},{"generated":{"line":23,"column":25},"source":"app/js/validation/dailyNoteValidate.js","original":{"line":17,"column":7}},{"generated":{"line":23,"column":27},"source":"app/js/validation/dailyNoteValidate.js","original":{"line":17,"column":34}},{"generated":{"line":24,"column":0},"source":"app/js/validation/dailyNoteValidate.js","original":{"line":18,"column":4}},{"generated":{"line":24,"column":8},"source":"app/js/validation/dailyNoteValidate.js","original":{"line":18,"column":8}},{"name":"third","generated":{"line":24,"column":10},"source":"app/js/validation/dailyNoteValidate.js","original":{"line":18,"column":10}},{"name":"value","generated":{"line":24,"column":16},"source":"app/js/validation/dailyNoteValidate.js","original":{"line":18,"column":16}},{"generated":{"line":24,"column":21},"source":"app/js/validation/dailyNoteValidate.js","original":{"line":18,"column":10}},{"name":"trim","generated":{"line":24,"column":22},"source":"app/js/validation/dailyNoteValidate.js","original":{"line":18,"column":22}},{"generated":{"line":24,"column":26},"source":"app/js/validation/dailyNoteValidate.js","original":{"line":18,"column":10}},{"name":"length","generated":{"line":24,"column":29},"source":"app/js/validation/dailyNoteValidate.js","original":{"line":18,"column":29}},{"generated":{"line":24,"column":35},"source":"app/js/validation/dailyNoteValidate.js","original":{"line":18,"column":10}},{"generated":{"line":24,"column":38},"source":"app/js/validation/dailyNoteValidate.js","original":{"line":18,"column":38}},{"generated":{"line":24,"column":39},"source":"app/js/validation/dailyNoteValidate.js","original":{"line":18,"column":8}},{"generated":{"line":24,"column":40},"source":"app/js/validation/dailyNoteValidate.js","original":{"line":18,"column":4}},{"generated":{"line":24,"column":42},"source":"app/js/validation/dailyNoteValidate.js","original":{"line":18,"column":42}},{"generated":{"line":25,"column":0},"source":"app/js/validation/dailyNoteValidate.js","original":{"line":19,"column":8}},{"generated":{"line":25,"column":15},"source":"app/js/validation/dailyNoteValidate.js","original":{"line":19,"column":15}},{"generated":{"line":25,"column":41},"source":"app/js/validation/dailyNoteValidate.js","original":{"line":19,"column":8}},{"generated":{"line":26,"column":0},"source":"app/js/validation/dailyNoteValidate.js","original":{"line":20,"column":5}},{"generated":{"line":26,"column":5},"source":"app/js/validation/dailyNoteValidate.js","original":{"line":18,"column":4}},{"generated":{"line":26,"column":11},"source":"app/js/validation/dailyNoteValidate.js","original":{"line":21,"column":9}},{"generated":{"line":27,"column":0},"source":"app/js/validation/dailyNoteValidate.js","original":{"line":22,"column":8}},{"generated":{"line":27,"column":15},"source":"app/js/validation/dailyNoteValidate.js","original":{"line":22,"column":15}},{"generated":{"line":27,"column":19},"source":"app/js/validation/dailyNoteValidate.js","original":{"line":22,"column":8}},{"generated":{"line":28,"column":0},"source":"app/js/validation/dailyNoteValidate.js","original":{"line":23,"column":5}},{"generated":{"line":29,"column":0},"source":"app/js/validation/dailyNoteValidate.js","original":{"line":24,"column":1}}],"sources":{"app/js/validation/dailyNoteValidate.js":"export function yesterday(first) {\n    if (!(first.value.trim().length > 3)) {\n        return 'Descrição muito pequena.';\n    }\n    else {\n        return null;\n    }\n}\nexport function today(today) {\n    if (!(today.value.trim().length > 3)) {\n        return 'Descrição muito pequena.';\n    }\n    else {\n        return null;\n    }\n}\nexport function impediment(third) {\n    if (!(third.value.trim().length > 3)) {\n        return 'Descrição muito pequena.';\n    }\n    else {\n        return null;\n    }\n}\n"},"lineCount":null}},"hash":"7104ca68659dd67905b7b5aae0283262","cacheData":{"env":{}}}